MANIFEST.in
README.md
REQUIREMENTS
REQUIREMENTS.django
UNLICENSE
distribute_setup.py
setup.py
src/facegraph/__init__.py
src/facegraph/fql.py
src/facegraph/graph.py
src/facegraph/django/__init__.py
src/facegraph/django/middleware.py
src/facegraph/django/views.py
src/pyfacegraph.egg-info/PKG-INFO
src/pyfacegraph.egg-info/SOURCES.txt
src/pyfacegraph.egg-info/dependency_links.txt
src/pyfacegraph.egg-info/requires.txt
src/pyfacegraph.egg-info/top_level.txt