Metadata-Version: 1.0
Name: pyfacegraph
Version: 0.0.4
Summary: A client library for the Facebook Graph API.
Home-page: http://github.com/iplatform/pyFaceGraph
Author: iPlatform Ltd
Author-email: opensource@theiplatform.com
License: UNKNOWN
Platform: UNKNOWN
